{"timestamp": "2026-07-16 04:31:00", "members": {"dogan": 1964, "I Am Dead  @_@": 1527, "Yata": 1480, "AangEX": 2268, "Feirisu": 1917, "[R23] Wolf \u2020": 1840, "MATHEMATRICK": 1086, "BlacKAkiresu O": 1495, "Tuyu|Fortuners": 1636, "Khakashi Hatake": 1508, "Ikhram ": 2604, "Prince G\u2122": 1670, "Yhwach Genryusai": 1447, "NicolasRicko": 2229, "Izx Hatake Jr": 1409, "ASHBORN\u2122": 1300, "Heisenberg ": 1313, "Tobirama Senju\u2122": 3029, "ZenithEX": 2467, "\u00a7\u00e5\u00f1\u00d0\u00e5\u00efm\u00e5r\u00b5 | Frtners": 1388, "Meru\u2122": 2563, "SNC | Vnzla Anbu |SN": 1606, "SNC | Signature": 1128, "Fusion": 1809, "Sesshomaru": 2539, "KYO": 1323, "SL41F3RT": 1775, "Lovebird | Gorelax": 1348, "ShadowRavenX": 2524, "SNC | TemperiTa": 2440, "SmallDino": 2020, "Breaker LITE": 1546, "Snoopy | Kokyotosu": 2491, "Arya": 1823, "Morrissey": 3209, "Jonny Brown": 2621, "Knightwalker": 1841, "a fucking ninja ": 1733, "Izx Infernity ": 1302, "Erza Scarlet": 2255}}