{"timestamp": "2026-07-15 00:07:20", "members": {"dogan": 228015, "I Am Dead  @_@": 202587, "Yata": 193206, "AangEX": 249317, "Feirisu": 218936, "[R23] Wolf \u2020": 134284, "MATHEMATRICK": 139006, "BlacKAkiresu O": 145170, "Tuyu|Fortuners": 18070, "Khakashi Hatake": 210341, "Ikhram ": 264812, "Prince G\u2122": 195073, "Yhwach Genryusai": 211468, "NicolasRicko": 376720, "Izx Hatake Jr": 204439, "ASHBORN\u2122": 144593, "Heisenberg ": 184234, "Tobirama Senju\u2122": 382999, "ZenithEX": 329118, "\u00a7\u00e5\u00f1\u00d0\u00e5\u00efm\u00e5r\u00b5 | Frtners": 197845, "Meru\u2122": 316432, "SNC | Vnzla Anbu |SN": 172053, "SNC | Signature": 141296, "Fusion": 286444, "Sesshomaru": 319508, "KYO": 164016, "SL41F3RT": 221813, "Lovebird | Gorelax": 190220, "ShadowRavenX": 237556, "SNC | TemperiTa": 216371, "SmallDino": 259267, "Breaker LITE": 206370, "Snoopy | Kokyotosu": 358691, "Arya": 238776, "Morrissey": 279151, "Jonny Brown": 281844, "Knightwalker": 137178, "a fucking ninja ": 286635, "Izx Infernity ": 181209, "Erza Scarlet": 357345}}