{"timestamp": "2026-07-18 23:31:00", "castles": {"Hiroshima": {"our_kills": 56418, "rival_kills": 19242, "rival_name": "Sangre Latina Crew", "our_rank": 1}, "Himeji": {"our_kills": 38, "rival_kills": 2026, "rival_name": "Shinigami Anbu", "our_rank": 3}, "Kumamoto": {"our_kills": 696, "rival_kills": 849, "rival_name": "Ninjas Born To Sleep", "our_rank": 6}, "Okazaki": {"our_kills": 7001, "rival_kills": 7086, "rival_name": "PILIPININJAS", "our_rank": 4}, "Inuyama": {"our_kills": 48385, "rival_kills": 19611, "rival_name": "Shinigami Anbu", "our_rank": 1}, "Gifu": {"our_kills": 534, "rival_kills": 840, "rival_name": "-45 DEG", "our_rank": 5}, "Hikone": {"our_kills": 23733, "rival_kills": 9507, "rival_name": "Ninjas Born To Fight", "our_rank": 1}}}