{"timestamp": "2026-07-19 04:31:00", "members": {"dogan": 3574, "I Am Dead  @_@": 3498, "Yata": 2611, "AangEX": 3767, "Feirisu": 3431, "[R23] Wolf \u2020": 3596, "MATHEMATRICK": 3058, "BlacKAkiresu O": 3182, "Tuyu|Fortuners": 2754, "Khakashi Hatake": 2792, "Ikhram ": 3882, "Prince G\u2122": 3359, "Yhwach Genryusai": 2787, "NicolasRicko": 3534, "Izx Hatake Jr": 2663, "ASHBORN\u2122": 2589, "Heisenberg ": 2642, "Tobirama Senju\u2122": 4812, "ZenithEX": 4152, "\u00a7\u00e5\u00f1\u00d0\u00e5\u00efm\u00e5r\u00b5 | Frtners": 2705, "Meru\u2122": 4153, "SNC | Vnzla Anbu |SN": 3256, "SNC | Signature": 3044, "Fusion": 3466, "Sesshomaru": 6419, "KYO": 2396, "SL41F3RT": 3317, "Lovebird | Gorelax": 2684, "ShadowRavenX": 4240, "SNC | TemperiTa": 4262, "SmallDino": 3502, "Breaker LITE": 3296, "Snoopy | Kokyotosu": 3791, "Arya": 3631, "Morrissey": 5075, "Jonny Brown": 4636, "Knightwalker": 3583, "a fucking ninja ": 3319, "Izx Infernity ": 2616, "Erza Scarlet": 3744}}