{"timestamp": "2026-07-18 06:01:00", "castles": {"Hiroshima": {"our_kills": 41945, "rival_kills": 17088, "rival_name": "Shinigami Anbu", "our_rank": 1}, "Himeji": {"our_kills": 38, "rival_kills": 1287, "rival_name": "Shinigami Anbu", "our_rank": 3}, "Kumamoto": {"our_kills": 695, "rival_kills": 745, "rival_name": "Ninjas Born To Sleep", "our_rank": 6}, "Okazaki": {"our_kills": 7001, "rival_kills": 9285, "rival_name": "Shinigami Anbu", "our_rank": 3}, "Inuyama": {"our_kills": 47982, "rival_kills": 19608, "rival_name": "Shinigami Anbu", "our_rank": 1}, "Gifu": {"our_kills": 534, "rival_kills": 840, "rival_name": "-45 DEG", "our_rank": 5}, "Hikone": {"our_kills": 22666, "rival_kills": 9360, "rival_name": "Ninjas Born To Fight", "our_rank": 1}}}